kickapi/__init__.py
kickapi/channel_data.py
kickapi/chat_data.py
kickapi/kickapi.py
kickapi/video_data.py
kickiso-0.3.4.dist-info/licenses/LICENSE
kickiso-0.3.4.dist-info/METADATA
kickiso-0.3.4.dist-info/WHEEL
kickiso-0.3.4.dist-info/top_level.txt
kickiso-0.3.4.dist-info/RECORD
