Metadata-Version: 2.4
Name: KickISO
Version: 0.3.4
Summary: A Python package for interacting with the Kick API to retrieve channel and video data.
Home-page: https://github.com/ISODev23/KickApiISO
Author: Tadeo
License: MIT
Keywords: kick,api,kickapi
License-File: LICENSE
Requires-Dist: cloudscraper
Dynamic: author
Dynamic: description
Dynamic: description-content-type
Dynamic: home-page
Dynamic: keywords
Dynamic: license
Dynamic: license-file
Dynamic: requires-dist
Dynamic: summary
